xiaoapi_redis/__init__.py
xiaoapi_redis/redis.py
xiaoapi_redis-0.0.3.dist-info/LICENSE
xiaoapi_redis-0.0.3.dist-info/METADATA
xiaoapi_redis-0.0.3.dist-info/WHEEL
xiaoapi_redis-0.0.3.dist-info/top_level.txt
xiaoapi_redis-0.0.3.dist-info/RECORD
